{
  "backendResilience": {},
  "inputVerification": {
    "url_verifications": [
      {
        "name": "example_configuration",
        "configuration": {
          "allowed_hosts": [
            "safetorun.com"
          ],
          "allowed_urls": [
            "https://safetorun.com?abc=def"
          ],
          "allowed_parameters": [],
          "allow_any_parameter": false,
          "allow_any_url": false
        }
      }
    ],
    "file_verifications": [
      {
        "name": "file_verifier",
        "configuration": {
          "allow_any_file": false,
          "allowed_exact_files": [
            "/data/data/com.blah/abc"
          ],
          "allowed_parent_directories": [
            {
              "directory": "/data/data/com.blah/parent",
              "allowSubdirectories": false
            }
          ]
        }
      }
    ]
  },
  "ondeviceResilience": {
    "blacklistedApps": [
      "com.abc"
    ],
    "allowedSignatures": [
      "ABASDASD",
      "BBBBBBB"
    ],
    "osCheckConfiguration": [
      {
        "allIntChecks": [
          {
            "intValue": 31,
            "comparator": "GREATER_THAN",
            "checkUuid": "913641b4-c6c5-4ac5-92af-5066a02e4133"
          }
        ],
        "unlessIntChecks": [
          {
            "intValue": 30,
            "comparator": "GREATER_THAN",
            "checkUuid": "944f1993-5931-41af-aae7-9b3be64d7d0a"
          }
        ]
      }
    ],
    "banDebugger": true
  }
}
